LICENSE
MANIFEST.in
README.md
pyproject.toml
setup.py
sjlt/__init__.py
sjlt/core.py
sjlt.egg-info/PKG-INFO
sjlt.egg-info/SOURCES.txt
sjlt.egg-info/dependency_links.txt
sjlt.egg-info/not-zip-safe
sjlt.egg-info/requires.txt
sjlt.egg-info/top_level.txt
sjlt/kernels/__init__.py
sjlt/kernels/sjlt_kernel.cu
test/test_sjlt.py