Metadata-Version: 2.4
Name: sjlt
Version: 0.1.6
Summary: Sparse Johnson-Lindenstrauss Transform with CUDA acceleration
Author: Pingbang Hu
Author-email: Pingbang Hu <pbb@illinois.edu>
License: MIT
Requires-Python: >=3.8
License-File: LICENSE
Requires-Dist: torch>=1.9.0
Requires-Dist: numpy>=1.19.0
Dynamic: author
Dynamic: license-file
Dynamic: requires-python
